boxb/__init__.py
boxb/bbox.py
boxb/consts.py
boxb/multibbox.py
boxb-1.1.1.dist-info/METADATA
boxb-1.1.1.dist-info/RECORD
boxb-1.1.1.dist-info/WHEEL
boxb-1.1.1.dist-info/top_level.txt
