Metadata-Version: 2.1
Name: boxb
Version: 1.1.1
Summary: Utilities for 2D bounding boxes
Home-page: https://github.com/amirmd76/box.git
Author: AmirMohammad Dehghan
Author-email: amirmd76@gmail.com
License: MIT
Platform: UNKNOWN
